ddaclient.py
integralclient.py
service_exception.py
integral_client_legacy-2.0.2.dist-info/COPYING
integral_client_legacy-2.0.2.dist-info/METADATA
integral_client_legacy-2.0.2.dist-info/WHEEL
integral_client_legacy-2.0.2.dist-info/top_level.txt
integral_client_legacy-2.0.2.dist-info/RECORD
