Metadata-Version: 2.1
Name: integral-client-legacy
Version: 2.0.2
Summary: integral client
Home-page: https://odahub.io
Author: V.S.
Author-email: contact@volodymyrsavchenko.com
License: GPL-2+
Classifier: Development Status :: 4 - Beta
Classifier: Environment :: Console
Classifier: Intended Audience :: Science/Research
Classifier: License :: OSI Approved :: GNU General Public License v2 or later (GPLv2+)
Classifier: Operating System :: POSIX
Classifier: Programming Language :: Python :: 2.7
Classifier: Programming Language :: Python :: 3.4
Classifier: Programming Language :: Python :: 3.5
Classifier: Programming Language :: Python :: 3.6
Classifier: Programming Language :: Python :: 3.7
Classifier: Topic :: Internet
Classifier: Topic :: Scientific/Engineering :: Astronomy
License-File: COPYING
Requires-Dist: lxml
Requires-Dist: six
Requires-Dist: coloredlogs
